setup.py
Keras_FB/__init__.py
Keras_FB/main.py
Keras_FB.egg-info/PKG-INFO
Keras_FB.egg-info/SOURCES.txt
Keras_FB.egg-info/dependency_links.txt
Keras_FB.egg-info/requires.txt
Keras_FB.egg-info/top_level.txt